aiocmd/__init__.py
aiocmd/aiocmd.py
aiocmd/nested_completer.py
aiocmd-0.1.5.dist-info/LICENSE
aiocmd-0.1.5.dist-info/METADATA
aiocmd-0.1.5.dist-info/WHEEL
aiocmd-0.1.5.dist-info/top_level.txt
aiocmd-0.1.5.dist-info/RECORD
